netbox_proxbox/__init__.py
netbox_proxbox/admin.py
netbox_proxbox/api/__init__.py
netbox_proxbox/api/serializers.py
netbox_proxbox/api/urls.py
netbox_proxbox/api/views.py
netbox_proxbox/example.py
netbox_proxbox/filters.py
netbox_proxbox/forms.py
netbox_proxbox/icon_classes.py
netbox_proxbox/migrations/0001_initial.py
netbox_proxbox/migrations/0002_vmresources_description.py
netbox_proxbox/migrations/0003_auto_20210419_2330.py
netbox_proxbox/migrations/__init__.py
netbox_proxbox/models.py
netbox_proxbox/navigation.py
netbox_proxbox/proxbox_api/README.md
netbox_proxbox/proxbox_api/__init__.py
netbox_proxbox/proxbox_api/create/__init__.py
netbox_proxbox/proxbox_api/create/dcim.py
netbox_proxbox/proxbox_api/create/extras.py
netbox_proxbox/proxbox_api/create/virtualization.py
netbox_proxbox/proxbox_api/plugins_config.py
netbox_proxbox/proxbox_api/remove.py
netbox_proxbox/proxbox_api/update.py
netbox_proxbox/proxbox_api/updates/__init__.py
netbox_proxbox/proxbox_api/updates/extras.py
netbox_proxbox/proxbox_api/updates/node.py
netbox_proxbox/proxbox_api/updates/virtual_machine.py
netbox_proxbox/release.py
netbox_proxbox/tables.py
netbox_proxbox/template_content.py
netbox_proxbox/templates/netbox_proxbox/footer.html
netbox_proxbox/templates/netbox_proxbox/home.html
netbox_proxbox/templates/netbox_proxbox/proxmox_vm.html
netbox_proxbox/templates/netbox_proxbox/proxmox_vm_delete.html
netbox_proxbox/templates/netbox_proxbox/proxmox_vm_edit.html
netbox_proxbox/templates/netbox_proxbox/proxmox_vm_full_update.html
netbox_proxbox/templates/netbox_proxbox/proxmox_vm_list.html
netbox_proxbox/templates/netbox_proxbox/update_result.html
netbox_proxbox/templates/netbox_proxbox/virtualmachine_proxmox_fields.html
netbox_proxbox/urls.py
netbox_proxbox/views.py
netbox_proxbox-0.0.5.dist-info/LICENSE
netbox_proxbox-0.0.5.dist-info/METADATA
netbox_proxbox-0.0.5.dist-info/WHEEL
netbox_proxbox-0.0.5.dist-info/RECORD
