Metadata-Version: 2.1
Name: netbox-proxbox
Version: 0.0.5
Summary: Netbox Plugin - Integrate Proxmox and Netbox
License: Apache-2.0
Author: Emerson Felipe
Author-email: emerson.felipe@nmultifibra.com
Requires-Python: >=3.8,<4.0
Classifier: License :: OSI Approved :: Apache Software License
Classifier: Programming Language :: Python :: 3
Classifier: Programming Language :: Python :: 3.8
Classifier: Programming Language :: Python :: 3.9
Classifier: Programming Language :: Python :: 3.10
Classifier: Programming Language :: Python :: 3.11
Requires-Dist: proxmoxer (>=2.0.1,<3.0.0)
Requires-Dist: pynetbox (>=7.0.1,<8.0.0)
